{
    "email": "shoity@gmail.com",
    "password": "shoity",
    "business_info": {
      "business_name": "Example Business",
      "business_address": "123 Business St, City, Country",
      "mailing_address": "PO Box 456, City, Country",
      "phone_number": "+1234567890",
      "logo_picture": null 
    },
    "business_details": {
      "industry_category": 1, 
      "description": "We are an example business operating since 2020.",
      "year_in_operation": 2020,
      "ownershipstructure": 1,  
      "trade_license_no": "TRADE-123456"
    },
    "branches": [
      {
        "branch_name": "Main Branch",
        "address": "456 Branch St, City, Country",
        "representative_name": "John Doe",
        "contact_number": "+9876543210",
        "email": "branch@example.com"
      },
      {
        "branch_name": "Second Branch",
        "address": "789 Branch St, City, Country",
        "representative_name": "Jane Doe",
        "contact_number": "+1122334455",
        "email": "branch2@example.com"
      }
    ],
    "owner_info": {
      "owner_name": "John Owner",
      "title": "CEO",
      "contact_number": "+1230984567",
      "owner_photo": null 
    }
  }